easycompletion/__init__.py
easycompletion/constants.py
easycompletion/logger.py
easycompletion/model.py
easycompletion/prompt.py
easycompletion-0.4.1.dist-info/LICENSE
easycompletion-0.4.1.dist-info/METADATA
easycompletion-0.4.1.dist-info/WHEEL
easycompletion-0.4.1.dist-info/top_level.txt
easycompletion-0.4.1.dist-info/RECORD
