Metadata-Version: 2.1
Name: easycompletion
Version: 0.4.1
Summary: Easy text completion and function calling. Also includes useful utilities for counting tokens, composing prompts and trimming them to fit within the token limit.
Home-page: https://github.com/AutonomousResearchGroup/easycompletion
Author: Moon
Author-email: shawmakesmagic@gmail.com
License: MIT
Classifier: Development Status :: 3 - Alpha
Classifier: Intended Audience :: Science/Research
Classifier: License :: OSI Approved :: MIT License
Classifier: Programming Language :: Python :: 3
Classifier: Operating System :: POSIX :: Linux
Classifier: Operating System :: MacOS :: MacOS X
Classifier: Operating System :: Microsoft :: Windows
License-File: LICENSE
Requires-Dist: openai
Requires-Dist: tiktoken
Requires-Dist: python-dotenv
Requires-Dist: rich
